aeon/__init__.py
aeonsdk-0.1.0.dist-info/METADATA
aeonsdk-0.1.0.dist-info/WHEEL
aeonsdk-0.1.0.dist-info/top_level.txt
aeonsdk-0.1.0.dist-info/RECORD
