Metadata-Version: 2.4
Name: aeonsdk
Version: 0.1.0
Summary: Aeon SDK for python
Author: Martin
Requires-Python: >=3.8
Requires-Dist: httpx
Requires-Dist: pydantic
